NiaogeDeLinuxSifangCaiJichuXuexiPianDisiban/README.md
NiaogeDeLinuxSifangCaiJichuXuexiPianDisiban/__init__.py
NiaogeDeLinuxSifangCaiJichuXuexiPianDisiban/__main__.py
NiaogeDeLinuxSifangCaiJichuXuexiPianDisiban/file.epub
NiaogeDeLinuxSifangCaiJichuXuexiPianDisiban/index.html
NiaogeDeLinuxSifangCaiJichuXuexiPianDisiban/css/__init__.py
NiaogeDeLinuxSifangCaiJichuXuexiPianDisiban/css/annotations.css
NiaogeDeLinuxSifangCaiJichuXuexiPianDisiban/css/main.css
NiaogeDeLinuxSifangCaiJichuXuexiPianDisiban/css/normalize.css
NiaogeDeLinuxSifangCaiJichuXuexiPianDisiban/css/popup.css
NiaogeDeLinuxSifangCaiJichuXuexiPianDisiban/font/__init__.py
NiaogeDeLinuxSifangCaiJichuXuexiPianDisiban/font/fontello.eot
NiaogeDeLinuxSifangCaiJichuXuexiPianDisiban/font/fontello.svg
NiaogeDeLinuxSifangCaiJichuXuexiPianDisiban/font/fontello.ttf
NiaogeDeLinuxSifangCaiJichuXuexiPianDisiban/font/fontello.woff
NiaogeDeLinuxSifangCaiJichuXuexiPianDisiban/img/__init__.py
NiaogeDeLinuxSifangCaiJichuXuexiPianDisiban/img/annotator-glyph-sprite.png
NiaogeDeLinuxSifangCaiJichuXuexiPianDisiban/img/annotator-icon-sprite.png
NiaogeDeLinuxSifangCaiJichuXuexiPianDisiban/img/apple-touch-icon.png
NiaogeDeLinuxSifangCaiJichuXuexiPianDisiban/img/cancelfullscreen.png
NiaogeDeLinuxSifangCaiJichuXuexiPianDisiban/img/close.png
NiaogeDeLinuxSifangCaiJichuXuexiPianDisiban/img/fullscreen.png
NiaogeDeLinuxSifangCaiJichuXuexiPianDisiban/img/loader.gif
NiaogeDeLinuxSifangCaiJichuXuexiPianDisiban/img/menu-icon.png
NiaogeDeLinuxSifangCaiJichuXuexiPianDisiban/img/save.png
NiaogeDeLinuxSifangCaiJichuXuexiPianDisiban/img/saved.png
NiaogeDeLinuxSifangCaiJichuXuexiPianDisiban/img/settings-s.png
NiaogeDeLinuxSifangCaiJichuXuexiPianDisiban/img/settings.png
NiaogeDeLinuxSifangCaiJichuXuexiPianDisiban/img/star.png
NiaogeDeLinuxSifangCaiJichuXuexiPianDisiban/js/__init__.py
NiaogeDeLinuxSifangCaiJichuXuexiPianDisiban/js/epub.js
NiaogeDeLinuxSifangCaiJichuXuexiPianDisiban/js/epub.min.js
niaoge_de_linux_sifang_cai_jichu_xuexi_pian_disiban-2024.3.1.0.dist-info/METADATA
niaoge_de_linux_sifang_cai_jichu_xuexi_pian_disiban-2024.3.1.0.dist-info/WHEEL
niaoge_de_linux_sifang_cai_jichu_xuexi_pian_disiban-2024.3.1.0.dist-info/entry_points.txt
niaoge_de_linux_sifang_cai_jichu_xuexi_pian_disiban-2024.3.1.0.dist-info/top_level.txt
niaoge_de_linux_sifang_cai_jichu_xuexi_pian_disiban-2024.3.1.0.dist-info/RECORD
